[
    {
        "title": "Фантастика",
        "addedClass": ""
    },
    {
        "title": "Романс",
        "addedClass": ""
    },
    {
        "title": "Романс",
        "addedClass": ""
    },
    {
        "title": "Романс",
        "addedClass": ""
    },
    {
        "title": "Романс",
        "addedClass": ""
    },
    {
        "title": "Романс",
        "addedClass": ""
    },
    {
        "title": "Фантастика",
        "addedClass": ""
    },
    {
        "title": "Романс",
        "addedClass": ""
    },
    {
        "title": "Ще щось...",
        "addedClass": ""
    },
    {
        "title": "Ще щось...",
        "addedClass": ""
    },
    {
        "title": "Ще щось...",
        "addedClass": ""
    },
    {
        "title": "Ще щось...",
        "addedClass": ""
    },
    {
        "title": "Ще щось...",
        "addedClass": ""
    },
    {
        "title": "Ще щось...",
        "addedClass": ""
    }
]